docx_locker/__init__.py
docx_locker/docx_locker.py
docx_locker/encrypt.py
docx_locker-0.7.2.dist-info/licenses/LICENSE
docx_locker-0.7.2.dist-info/METADATA
docx_locker-0.7.2.dist-info/WHEEL
docx_locker-0.7.2.dist-info/top_level.txt
docx_locker-0.7.2.dist-info/RECORD
