Metadata-Version: 2.4
Name: docx-locker
Version: 0.7.2
Summary: Python module for enabling document protection on docx files
License: MIT License
Keywords: docx,documentProtection
Classifier: Development Status :: 5 - Production/Stable
Classifier: License :: OSI Approved :: MIT License
Classifier: Operating System :: OS Independent
Classifier: Programming Language :: Python
Classifier: Programming Language :: Python :: 3 :: Only
Classifier: Programming Language :: Python :: 3.10
Classifier: Programming Language :: Python :: 3.11
Classifier: Programming Language :: Python :: 3.12
Classifier: Programming Language :: Python :: 3.13
Classifier: Programming Language :: Python :: Implementation :: PyPy
Classifier: Topic :: Office/Business :: Office Suites
Requires-Python: >=3.10
License-File: LICENSE
Requires-Dist: lxml>=5.3.0
Dynamic: license-file
